Workbook

Sheet Summary
A1: BrightLine HR - API Integration Health: cost summary
A3: Item | B3: USD
A4: One-time delivery effort (incl. contingency) | B4: ='One-time setup'!$C$17 -> 69517.5
A5: Monthly run cost (Azure-aligned stack) | B5: ='Monthly run cost'!$C$16 -> 1029.0459
A6: Run cost included in setup budget | B6: ='One-time setup'!$C$19-'One-time setup'!$C$17 -> 3087.1378
A7: INITIAL SETUP BUDGET | B7: ='One-time setup'!$C$19 -> 72604.638
A8: Year-1 total (effort + 12 months run) | B8: ='One-time setup'!$C$17+'Monthly run cost'!$C$16*12 -> 81866.051
A9: Run cost with ADX Dev/Test (no SLA) - saving vs chosen option /month | B9: ='Monthly run cost'!$C$16-('Monthly run cost'!$C$16-IF(Assumptions!$B$16=1,0,2*'Unit prices'!$B$7*Assumptions!$B$15-'Unit prices'!$B$6*Assumptions!$B$15)) -> 467.2
A11: Read this first
A12: 1. Unit prices are planning estimates and were NOT verified against live Microsoft price pages. Replace them on the 'Unit prices' sheet (blue cells).
A13: 2. Event volume is not in the case study; 2M events/day is a placeholder. At this volume Event Hubs and Functions are minor; ADX and Grafana dominate.
A14: 3. Delivery rate (USD 650/day) is a placeholder, not an HCLTech rate. Effort days are a bottom-up estimate for V1 scope only (V2/V3 excluded).
A15: 4. The working prototype (zip) already covers the engine, API and a dashboard, so it de-risks the engine/serve workstreams; no discount is applied.
A16: 5. Excludes taxes, support plans, data egress, ServiceNow/Jira, ML and LLM digest (V2/V3), and any customer-side network (VPN/ExpressRoute) costs.

Sheet Assumptions
A1: BrightLine HR - API Integration Health: cost assumptions
A2: Blue = editable input. Yellow = key assumption to confirm. All unit prices are PLANNING ESTIMATES (USD list, pay-as-you-go) NOT verified against live Azure/Microsoft price pages - confirm in the Azure Pricing Calculator before quoting.
A4: Assumption | B4: Value | C4: Unit | D4: Note / source
A5: Events per day (V1 start) | B5: 2000000 | C5: events/day | D5: NOT in the case study (deck slide 9 asks to confirm). Placeholder.
A6: Annual growth | B6: 0.1 | C6: % | D6: Deck slide 2: 10% growth
A7: Average event size | B7: 0.5 | C7: KB | D7: Assumed request-log row incl. keys
A8: Retention - raw | B8: 60 | C8: days | D8: Deck slide 2
A9: Blended delivery rate | B9: 650 | C9: USD / person-day | D9: PLACEHOLDER - replace with HCLTech/BrightLine rate card
A10: Contingency on effort | B10: 0.15 | C10: % | D10: Assumed
A11: Months of run cost in 'initial setup' budget | B11: 3 | C11: months | D11: Build + UAT + first live quarter
A12: Executive Power BI users | B12: 5 | C12: users | D12: Assumed (deck: Executives)
A13: Ops/Support/Eng Grafana users | B13: 15 | C13: users | D13: Assumed
A14: Power Automate flow owners (Premium) | B14: 1 | C14: users | D14: Teams webhook flow; Teams Workflows may remove this cost
A15: Hours per month | B15: 730 | C15: h
A16: ADX option for V1 (1=Dev/Test no SLA, 2=Production 2-node) | B16: 2 | C16: switch | D16: Deck needs 99% uptime 24x7 -> option 2 recommended

Sheet Unit prices
A1: Unit prices (USD) - planning estimates, UNVERIFIED
A3: Item | B3: Price | C3: Unit | D3: Basis
A4: Event Hubs Standard - throughput unit | B4: 0.03 | C4: per TU-hour | D4: Approx. list price; 1 TU is ample for assumed volume
A5: Event Hubs - ingress | B5: 0.028 | C5: per million events | D5: Approx. list price
A6: ADX Dev/Test (E2a_v4) incl. markup | B6: 0.2 | C6: per hour | D6: Approx.; no SLA
A7: ADX Production D11_v2 node incl. markup | B7: 0.42 | C7: per node-hour | D7: Approx.; 2 nodes for SLA
A8: ADX storage (hot+cold) | B8: 0.03 | C8: per GB-month | D8: Approx. (blob-backed)
A9: Container Apps - 2 replicas, 0.5 vCPU / 1 GiB, mostly idle | B9: 40 | C9: per month | D9: Estimate from consumption rates; free grant ignored
A10: Azure Functions (consumption) - mask & validate | B10: 10 | C10: per month | D10: Estimate, low volume
A11: Managed Grafana Standard - instance | B11: 130 | C11: per month | D11: Approx.; verify tier
A12: Managed Grafana - active user | B12: 6 | C12: per user-month | D12: Approx.
A13: Power BI Pro | B13: 14 | C13: per user-month | D13: Public list price (verify)
A14: Power Automate Premium | B14: 15 | C14: per user-month | D14: Public list price (verify)
A15: Key Vault | B15: 2 | C15: per month | D15: Few secrets/ops
A16: Log Analytics / Azure Monitor | B16: 25 | C16: per month | D16: ~10 GB logs + alerts
A17: Container Registry Basic | B17: 5 | C17: per month
A18: Blob (dead-letter, Terraform state) | B18: 3 | C18: per month

Sheet Sizing
A1: Data sizing
A3: Metric | B3: Value | C3: Unit
A4: Events per month | B4: =Assumptions!$B$5*30 -> 60000000 | C4: events
A5: Raw GB per month | B5: =B4*Assumptions!$B$7/1024/1024 -> 28.610229 | C5: GB
A6: Raw GB held (retention) | B6: =B5/30*Assumptions!$B$8 -> 57.220459 | C6: GB
A7: Aggregates & cache (assumed 20% of raw held) | B7: =B6*0.2 -> 11.444092 | C7: GB
A8: Total ADX storage, year 1 end (growth applied) | B8: =(B6+B7)*(1+Assumptions!$B$6) -> 75.531006 | C8: GB

Sheet Monthly run cost
A1: Monthly infrastructure run cost - Azure-aligned V1 stack (deck slide 5)
A3: Layer | B3: Service (deck) | C3: Monthly USD | D3: How calculated
A4: Ingest | B4: Azure Event Hubs Standard | C4: =1*'Unit prices'!$B$4*Assumptions!$B$15+Sizing!B4/1000000*'Unit prices'!$B$5 -> 23.58 | D4: 1 TU x hours + ingress per million events
A5: Mask & validate | B5: Azure Functions (Python) | C5: ='Unit prices'!$B$10 -> 10 | D5: flat estimate
A6: Store | B6: Azure Data Explorer | C6: =IF(Assumptions!$B$16=1,'Unit prices'!$B$6*Assumptions!$B$15,2*'Unit prices'!$B$7*Assumptions!$B$15)+Sizing!B8*'Unit prices'!$B$8 -> 615.46593 | D6: Dev/Test 1 node, or 2 production nodes, + storage
A7: Health engine | B7: Timer job (runs in the API container) | C7: 0 | D7: hourly job; no separate cost in prototype design
A8: Serve | B8: FastAPI on Azure Container Apps | C8: ='Unit prices'!$B$9 -> 40 | D8: flat estimate
A9: Serve | B9: Container Registry | C9: ='Unit prices'!$B$17 -> 5
A10: Dashboard | B10: Azure Managed Grafana (Standard) | C10: ='Unit prices'!$B$11+Assumptions!$B$13*'Unit prices'!$B$12 -> 220 | D10: instance + active users
A11: Dashboard | B11: Power BI Pro (executives) | C11: =Assumptions!$B$12*'Unit prices'!$B$13 -> 70 | D11: users x price
A12: Alerts | B12: Power Automate Premium (Teams webhook) | C12: =Assumptions!$B$14*'Unit prices'!$B$14 -> 15 | D12: users x price
A13: Security & ops | B13: Key Vault | C13: ='Unit prices'!$B$15 -> 2
A14: Security & ops | B14: Azure Monitor / Log Analytics | C14: ='Unit prices'!$B$16 -> 25
A15: Security & ops | B15: Blob storage (dead-letter, TF state) | C15: ='Unit prices'!$B$18 -> 3
B16: Total per month | C16: =SUM(C4:C15) -> 1029.0459
B17: Total per year | C17: =C16*12 -> 12348.551
B18: Contingency-free; excludes Entra ID (included in M365 licences), networking egress, support plan, taxes

Sheet One-time setup
A1: One-time initial setup (V1 scope, deck slide 9) - effort-based
A3: Workstream | B3: Person-days | C3: Cost USD | D3: Note
A4: Discovery, sizing & sign-off (weights, SLA, tenancy, volumes) | B4: 8 | C4: =B4*Assumptions!$B$9 -> 5200 | D4: Open items on deck slide 9
A5: Azure landing: Terraform, networking, Entra roles, Key Vault | B5: 12 | C5: =B5*Assumptions!$B$9 -> 7800 | D5: Skeleton provided in zip
A6: Ingest: Event Hubs + Functions (schema check, PII masking) | B6: 10 | C6: =B6*Assumptions!$B$9 -> 6500 | D6: Logic in app/ingest.py, masking.py is reusable
A7: Store: ADX schema, 60-day retention, hourly aggregates | B7: 8 | C7: =B7*Assumptions!$B$9 -> 5200 | D7: KQL starter in zip
A8: Health engine: hourly job, baselines, scoring, roll-up | B8: 12 | C8: =B8*Assumptions!$B$9 -> 7800 | D8: Prototype engine.py is the reference implementation
A9: Serve: Health API (FastAPI) + container pipeline + CI/CD | B9: 8 | C9: =B9*Assumptions!$B$9 -> 5200 | D9: Prototype main.py reusable
A10: Grafana operations dashboards + role-based views | B10: 10 | C10: =B10*Assumptions!$B$9 -> 6500
A11: Power BI executive report | B11: 6 | C11: =B11*Assumptions!$B$9 -> 3900
A12: Teams alerts via Power Automate, dedupe, escalation rules | B12: 4 | C12: =B12*Assumptions!$B$9 -> 2600
A13: Testing, performance (<10 s load), UAT, security review | B13: 10 | C13: =B13*Assumptions!$B$9 -> 6500
A14: Documentation, runbook, training & hypercare handover | B14: 5 | C14: =B14*Assumptions!$B$9 -> 3250
A15: Subtotal | B15: =SUM(B4:B14) -> 93 | C15: =SUM(C4:C14) -> 60450
A16: Contingency | B16: =B15*Assumptions!$B$10 -> 13.95 | C16: =B16*Assumptions!$B$9 -> 9067.5
A17: Total one-time delivery effort | B17: =B15+B16 -> 106.95 | C17: =C15+C16 -> 69517.5
A18: Run cost during build / first live quarter | C18: ='Monthly run cost'!$C$16*Assumptions!$B$11 -> 3087.1378
A19: INITIAL SETUP BUDGET (effort + infra months) | C19: =C17+C18 -> 72604.638
